geoclustering/__init__.py
geoclustering/__main__.py
geoclustering/clustering.py
geoclustering/encoding.py
geoclustering/io.py
geoclustering/kepler_config.json
geoclustering/version.py
geoclustering-0.4.1.dist-info/LICENSE
geoclustering-0.4.1.dist-info/METADATA
geoclustering-0.4.1.dist-info/WHEEL
geoclustering-0.4.1.dist-info/entry_points.txt
geoclustering-0.4.1.dist-info/top_level.txt
geoclustering-0.4.1.dist-info/RECORD
