Metadata-Version: 2.1
Name: geoclustering
Version: 0.4.1
Summary: 📍 command-line tool for clustering geolocations.
Author: Bellingcat
Author-email: tech@bellingcat.com
License: MIT
Keywords: cluster,gis,pattern-analysis
Classifier: Intended Audience :: Developers
Classifier: Intended Audience :: Science/Research
Classifier: License :: OSI Approved :: MIT License
Classifier: Programming Language :: Python :: 3
License-File: LICENSE
Requires-Dist: click
Requires-Dist: geojson
Requires-Dist: numpy
Requires-Dist: pandas
Requires-Dist: scikit-learn
Provides-Extra: dev
Requires-Dist: black ; extra == 'dev'
Requires-Dist: wheel ; extra == 'dev'
Requires-Dist: pre-commit ; extra == 'dev'
Requires-Dist: pytest ; extra == 'dev'
Provides-Extra: full
Requires-Dist: keplergl ; extra == 'full'
